mypythproject/DashBoard.py
mypythproject/__init__.py
mypythproject/mypythproject.py
mypythproject/optimization_techniques.py
mypythproject/sp500_companies.csv
mypythproject/tickers.py
mypythproject-0.1.1.dist-info/LICENSE
mypythproject-0.1.1.dist-info/METADATA
mypythproject-0.1.1.dist-info/WHEEL
mypythproject-0.1.1.dist-info/RECORD
