Metadata-Version: 2.1
Name: mypythproject
Version: 0.1.1
Summary: An extension of pybacktestchain that enhances portfolio optimization and backtesting with advanced features.
License: MIT
Author: Amine Lahlou
Requires-Python: >=3.11,<4.0
Classifier: License :: OSI Approved :: MIT License
Classifier: Programming Language :: Python :: 3
Classifier: Programming Language :: Python :: 3.11
Classifier: Programming Language :: Python :: 3.12
Classifier: Programming Language :: Python :: 3.13
Requires-Dist: dash (>=2.18.2,<3.0.0)
Requires-Dist: matplotlib (>=3.10.0,<4.0.0)
Requires-Dist: numba (>=0.60.0,<0.61.0)
Requires-Dist: pybacktestchain (>=0.2.1,<0.3.0)
